{
  "id": "api-reference/organizations",
  "title": "Organizations API",
  "description": "White-label and organization-scoped agents. Use headers: x-api-key, x-api-secret.",
  "source": "@site/docs/api-reference/organizations.md",
  "sourceDirName": "api-reference",
  "slug": "/api-reference/organizations",
  "permalink": "/clawpay-docs/docs/api-reference/organizations",
  "draft": false,
  "unlisted": false,
  "editUrl": "https://github.com/clawpay/clawpay-docs/tree/main/docs/api-reference/organizations.md",
  "tags": [],
  "version": "current",
  "sidebarPosition": 11,
  "frontMatter": {
    "sidebar_position": 11
  },
  "sidebar": "docsSidebar",
  "previous": {
    "title": "Insurance API (Phase 3)",
    "permalink": "/clawpay-docs/docs/api-reference/insurance"
  },
  "next": {
    "title": "Phase 2 Features",
    "permalink": "/clawpay-docs/docs/advanced/phase2-features"
  }
}